deepserializers/__init__.py
deepserializers/renderers.py
deepserializers/serializers.py
deepserializers/utils.py
deepserializers/views.py
djangorestframework_deepserializers-0.1.dist-info/LICENSE
djangorestframework_deepserializers-0.1.dist-info/METADATA
djangorestframework_deepserializers-0.1.dist-info/WHEEL
djangorestframework_deepserializers-0.1.dist-info/top_level.txt
djangorestframework_deepserializers-0.1.dist-info/RECORD
