Metadata-Version: 2.1
Name: djangorestframework-deepserializers
Version: 0.1
Summary: A package to create deep Serializers and ModelViewSet for django rest-framework
Home-page: https://github.com/enzofrnt/djangorestframework-deepserializers
Author: Made by enzo_frnt from the Horou repo
Keywords: Django,Django REST Framework,Deep,Depth,serializer,viewset,nested,nested serializer
License-File: LICENSE
Requires-Dist: Django
Requires-Dist: djangorestframework
